LICENSE
MANIFEST.in
README.md
README.rst
setup.py
pysbw/__init__.py
pysbw/_version.py
pysbw.egg-info/PKG-INFO
pysbw.egg-info/SOURCES.txt
pysbw.egg-info/dependency_links.txt
pysbw.egg-info/not-zip-safe
pysbw.egg-info/requires.txt
pysbw.egg-info/top_level.txt