Metadata-Version: 1.1
Name: pysbw
Version: 0.1a10
Summary: Python API Implementation for Accessing Stopbadware Data Feed
Home-page: https://bitbucket.org/arman_noroozian/pysbw
Author: Arman Noroozian
Author-email: arman.noroozian.developer@gmail.com
License: MIT
Keywords: stopbadware api download
Platform: UNKNOWN
Classifier: Development Status :: 3 - Alpha
Classifier: Intended Audience :: Developers
Classifier: Topic :: Software Development :: Libraries :: Python Modules
Classifier: Topic :: Security
Classifier: License :: OSI Approved :: MIT License
Classifier: Operating System :: OS Independent
Classifier: Programming Language :: Python
Classifier: Programming Language :: Python :: 3
